virtualembed/__init__.py
virtualembed/embedimage.py
virtualembed/virtualembed.py
virtualembed-0.0.12.dist-info/LICENSE.txt
virtualembed-0.0.12.dist-info/METADATA
virtualembed-0.0.12.dist-info/WHEEL
virtualembed-0.0.12.dist-info/top_level.txt
virtualembed-0.0.12.dist-info/RECORD
