Metadata-Version: 2.1
Name: virtualembed
Version: 0.0.12
Summary: A package for visualize discord embeds
Home-page: https://github.com/Fenish/VirtualEmbed
Author: Fenish
Author-email: sohretalhadev@gmail.com
License: UNKNOWN
Project-URL: Bug Tracker, https://github.com/Fenish/VirtualEmbed/issues
Platform: UNKNOWN
Classifier: Programming Language :: Python :: 3
Classifier: License :: OSI Approved :: MIT License
Classifier: Operating System :: OS Independent
Requires-Python: >=3.6
License-File: LICENSE.txt
